column/__init__.py
column/api_runner.py
column/callback.py
column/exceptions.py
column/runner.py
column/subprocess_runner.py
column/utils.py
column/api/__init__.py
column/api/run.py
column/api/wsgi.py
column/api/backend/__init__.py
column/api/backend/cache/__init__.py
column/api/backend/cache/local_mem.py
column/api/backend/cache/store.py
column/api/common/__init__.py
column/api/common/utils.py
column/api/controller/__init__.py
column/api/controller/credential_controller.py
column/api/controller/run_controller.py
column/api/manager/__init__.py
column/api/manager/credential_manager.py
column/api/manager/run_manager.py
column/api/model/__init__.py
column/api/model/run_model.py
column/api/objects/__init__.py
column/plugins/__init__.py
column/plugins/callback/__init__.py
column/plugins/callback/progress.py
column-0.5.0.dist-info/DESCRIPTION.rst
column-0.5.0.dist-info/METADATA
column-0.5.0.dist-info/RECORD
column-0.5.0.dist-info/WHEEL
column-0.5.0.dist-info/metadata.json
column-0.5.0.dist-info/top_level.txt
etc/column/column.conf
etc/column/uwsgi.ini
tests/__init__.py
tests/test_api_runner.py
tests/test_exceptions.py
tests/test_utils.py
tests/api/__init__.py
tests/api/controllers/__init__.py
tests/api/controllers/test_credential.py
tests/api/controllers/test_run.py
