Metadata-Version: 2.0
Name: column
Version: 0.5.0
Summary: A thin wrapper on top of ansible with a stable API.
Home-page: https://github.com/vmware/column
Author: VMware
Author-email: UNKNOWN
License: GPL-3.0
Platform: any
Classifier: Development Status :: 3 - Alpha
Classifier: Intended Audience :: Developers
Classifier: Intended Audience :: Information Technology
Classifier: Operating System :: POSIX :: Linux
Classifier: License :: OSI Approved :: GNU General Public License v3 (GPLv3)
Classifier: Programming Language :: Python
Classifier: Programming Language :: Python :: 2
Classifier: Programming Language :: Python :: 2.7
Requires-Dist: ansible (>=2.2.0.0)
Requires-Dist: cryptography (!=2.0.1)
Requires-Dist: flask
Requires-Dist: flask-restful
Requires-Dist: jsonschema
Requires-Dist: six
